kalyan_ai/__init__.py
kalyan_ai/api_server.py
kalyan_ai-1.0.6.dist-info/licenses/LICENSE
kalyan_ai-1.0.6.dist-info/METADATA
kalyan_ai-1.0.6.dist-info/WHEEL
kalyan_ai-1.0.6.dist-info/entry_points.txt
kalyan_ai-1.0.6.dist-info/top_level.txt
kalyan_ai-1.0.6.dist-info/RECORD
